numbannotate/__init__.py
numbannotate-0.0.3.dist-info/LICENSE
numbannotate-0.0.3.dist-info/WHEEL
numbannotate-0.0.3.dist-info/METADATA
numbannotate-0.0.3.dist-info/RECORD
