Metadata-Version: 1.2
Name: numbannotate
Version: 0.0.3
Summary: Provide a simple magic that emits html annotated python code to find potential perf improvements
Home-page: https://github.com/Carreau/numbannotate
License: UNKNOWN
Author: Matthias Bussonnier
Author-email: bussonniermatthias@gmail.com
Classifier: License :: OSI Approved :: MIT License
